pyopenbot/__init__.py
pyopenbot/__main__.py
pyopenbot/character.py
pyopenbot/main.py
pyopenbot/cli/CLI.py
pyopenbot/cli/__init__.py
pyopenbot/commands/__init__.py
pyopenbot/commands/base_command.py
pyopenbot/commands/check.py
pyopenbot/commands/init.py
pyopenbot/commands/run.py
pyopenbot/platforms/__init__.py
pyopenbot/platforms/base_platform.py
pyopenbot/platforms/cli_platform.py
pyopenbot-0.3.0.dist-info/METADATA
pyopenbot-0.3.0.dist-info/WHEEL
pyopenbot-0.3.0.dist-info/entry_points.txt
pyopenbot-0.3.0.dist-info/licenses/LICENSE
pyopenbot-0.3.0.dist-info/RECORD
