Metadata-Version: 2.4
Name: pyopenbot
Version: 0.3.0
Summary: Add your description here
Author-email: Jason Scheffel <contact@jasonscheffel.com>
License: BSD 3-Clause License
License-File: LICENSE
Requires-Python: >=3.12
Requires-Dist: discord-py[voice]>=2.4.0
Requires-Dist: litellm>=1.57.4
Requires-Dist: pyyaml>=6.0.2
Requires-Dist: typer>=0.15.1
